{"cameraMode":{"drawMode":0,"name":"Shaded","section":"Shading Mode"},"sceneLighting":true,"audioPlay":false,"sceneViewState":{"showFog":true,"showMaterialUpdate":false,"showSkybox":true,"showFlares":true,"showImageEffects":true,"showParticleSystems":true},"in2DMode":false,"pivot":{"x":-3.951892852783203,"y":17.546554565429689,"z":25.387046813964845},"rotation":{"x":0.4535352885723114,"y":-0.13148045539855958,"z":0.06784997880458832,"w":0.8788741827011108},"size":175.30624389648438,"orthographic":false}